ql_uncertainty/__init__.py
ql_uncertainty/baselines.py
ql_uncertainty/inference.py
ql_uncertainty/internal_confidence.py
ql_uncertainty/utils.py
query_level_uncertainty-0.0.2.dist-info/METADATA
query_level_uncertainty-0.0.2.dist-info/WHEEL
query_level_uncertainty-0.0.2.dist-info/licenses/LICENSE
query_level_uncertainty-0.0.2.dist-info/RECORD
